dl1_data_handler/__init__.py
dl1_data_handler/containers.py
dl1_data_handler/dl_eventsources.py
dl1_data_handler/filters.py
dl1_data_handler/image_mapper.py
dl1_data_handler/processor.py
dl1_data_handler/reader.py
dl1_data_handler/table_definitions.py
dl1_data_handler/transforms.py
dl1_data_handler/writer.py
dl1_data_handler_light-0.9.0.dist-info/AUTHORS
dl1_data_handler_light-0.9.0.dist-info/LICENSE
dl1_data_handler_light-0.9.0.dist-info/METADATA
dl1_data_handler_light-0.9.0.dist-info/WHEEL
dl1_data_handler_light-0.9.0.dist-info/top_level.txt
dl1_data_handler_light-0.9.0.dist-info/zip-safe
dl1_data_handler_light-0.9.0.dist-info/RECORD
